stencils/__init__.py
stencils-0.1.8.dist-info/licenses/LICENSE
stencils-0.1.8.dist-info/METADATA
stencils-0.1.8.dist-info/WHEEL
stencils-0.1.8.dist-info/top_level.txt
stencils-0.1.8.dist-info/RECORD
