Metadata-Version: 2.4
Name: stencils
Version: 0.1.8
Summary: A simple templates loader
Author-email: "Ioannis D (devcoons)" <support@devcoons.com>
License: MIT License
Project-URL: Homepage, https://github.com/devcoons/stencils
Project-URL: Issues, https://github.com/devcoons/stencils/issues
Keywords: templates,load
Classifier: Development Status :: 5 - Production/Stable
Classifier: Intended Audience :: Developers
Classifier: Natural Language :: English
Classifier: License :: OSI Approved :: MIT License
Classifier: Operating System :: OS Independent
Classifier: Programming Language :: Python :: 3.9
Classifier: Programming Language :: Python :: 3.10
Classifier: Programming Language :: Python :: 3.11
Classifier: Programming Language :: Python :: 3.12
Classifier: Programming Language :: Python :: Implementation :: PyPy
Requires-Python: >=3.9
License-File: LICENSE
Provides-Extra: dev
Requires-Dist: pip-tools; extra == "dev"
Dynamic: license-file
